numext/__init__.py
numext/number_extractor.py
numext-0.0.7.dist-info/LICENSE
numext-0.0.7.dist-info/METADATA
numext-0.0.7.dist-info/WHEEL
numext-0.0.7.dist-info/top_level.txt
numext-0.0.7.dist-info/RECORD
